novawiz
