Metadata-Version: 1.0
Name: novawiz
Version: 0.0.13
Summary: a command-line wizard for nova
Home-page: github.com/echohead/novawiz
Author: tim miller
Author-email: name@example.com
License: UNKNOWN
Platform: UNKNOWN
